Module/__init__.py
Datarbased_speedest-56.0.5.260.13.dist-info/METADATA
Datarbased_speedest-56.0.5.260.13.dist-info/WHEEL
Datarbased_speedest-56.0.5.260.13.dist-info/top_level.txt
Datarbased_speedest-56.0.5.260.13.dist-info/RECORD
