Metadata-Version: 2.1
Name: Datarbased-speedest
Version: 56.0.5.260.13
Summary: This is the simplest module for quick work with databases3.
Home-page: https://github.com/UserSal1/
Author: romaska555
Author-email: example@gmail.com
Project-URL: GitHub, https://github.com/UserSal1/
Keywords: datas databased
Classifier: Programming Language :: Python :: 3.12
Classifier: License :: OSI Approved :: MIT License
Classifier: Operating System :: OS Independent
Requires-Python: >=3.6
Requires-Dist: requests >=2.25.1
